{
  "jsonSchemaSemanticVersion": "1.0.0",
  "imports": [
    {
      "corpusPath": "/foundations.cdm.json"
    }
  ],
  "definitions": [
    {
      "entityName": "BankAcountMasterData",
      "hasAttributes": [
        {
          "name": "bankAccountId",
          "purpose": "hasA",
          "dataType": "string"
        },
        {
          "name": "bankAccountNumber",
          "purpose": "hasA",
          "dataType": "decimal"
        },
        {
          "name": "bankSortCode",
          "purpose": "hasA",
          "dataType": "string"
        },
        {
          "name": "IBAN",
          "purpose": "hasA",
          "dataType": "string"
        },
        {
          "name": "bankAccountType",
          "purpose": "hasA",
          "dataType": "string"
        },
        {
          "name": "bankAccountSubType",
          "purpose": "hasA",
          "dataType": "string"
        }
      ]
    }
  ]
}